{
	"id": "vj04im9k5eg",
	"x": 55.999999999999986,
	"y": 56.00000000000001,
	"width": 32.000000000000014,
	"height": 35.99999999999999,
	"links": [
		{
			"id": "eenldim7oc8",
			"from": {
				"path": [
					{
						"boxId": "vj04im9k5eg",
						"boxName": "vj04im9k5eg",
						"x": 15.999999999999998,
						"y": 23.99999999999999
					}
				],
				"floatToBorder": true
			},
			"to": {
				"path": [
					{
						"boxId": "vj04im9k5eg",
						"boxName": "vj04im9k5eg",
						"x": 84.00000000000004,
						"y": 23.99999999999999
					}
				],
				"floatToBorder": true
			}
		}
	]
}